.travis.yml
README.md
requirements.txt
setup.py
autorounddecimal/__init__.py
autorounddecimal/core.hy
autorounddecimal.egg-info/PKG-INFO
autorounddecimal.egg-info/SOURCES.txt
autorounddecimal.egg-info/dependency_links.txt
autorounddecimal.egg-info/requires.txt
autorounddecimal.egg-info/top_level.txt
tests/__init__.py
tests/test_hy.hy
tests/test_py.py